BML/__init__.py
BML_bgp-1.0.dist-info/LICENSE
BML_bgp-1.0.dist-info/METADATA
BML_bgp-1.0.dist-info/WHEEL
BML_bgp-1.0.dist-info/top_level.txt
BML_bgp-1.0.dist-info/RECORD
