Metadata-Version: 2.1
Name: BML-bgp
Version: 1.0
Summary: BML: An Efficient and Versatile Tool for BGP Dataset Collection
Home-page: UNKNOWN
Author: Kevin Hoarau
Author-email: kevin.hoarau@univ-reunion.fr
License: UNKNOWN
Platform: UNKNOWN
